dingtalk_app_accesstoken_refresh/__init__.py
dingtalk_app_accesstoken_refresh/_cache_source/local_cache.py
dingtalk_app_accesstoken_refresh/_cache_source/types.py
dingtalk_app_accesstoken_refresh/_client.py
dingtalk_app_accesstoken_refresh/_constants.py
dingtalk_app_accesstoken_refresh/_errors.py
dingtalk_app_accesstoken_refresh/_types.py
dingtalk_app_accesstoken_refresh/py.typed
dingtalk_app_accesstoken_refresh-0.1.0.dist-info/WHEEL
dingtalk_app_accesstoken_refresh-0.1.0.dist-info/METADATA
dingtalk_app_accesstoken_refresh-0.1.0.dist-info/RECORD
