Metadata-Version: 2.3
Name: dingtalk-app-accesstoken-refresh
Version: 0.1.0
Summary: DingTalk App AccessToken Refresh Tool
Author: Martian Bugs
Requires-Dist: requests>=2.32.5,<3.0.0
Requires-Dist: tinydb>=4.8.2,<5.0.0
Requires-Python: >=3.12
